install_scripts/__init__.py
install_scripts/arch.py
install_scripts/auth.py
install_scripts/bashrc.py
install_scripts/configs.py
install_scripts/cryptomining.py
install_scripts/customization.py
install_scripts/distros.py
install_scripts/helper.py
install_scripts/hosts.py
install_scripts/ubuntu.py
install_scripts-0.1.6.data/scripts/bashrc-gen
install_scripts-0.1.6.data/scripts/install-scripts
test/__init__.py
install_scripts-0.1.6.dist-info/LICENSE
install_scripts-0.1.6.dist-info/METADATA
install_scripts-0.1.6.dist-info/WHEEL
install_scripts-0.1.6.dist-info/top_level.txt
install_scripts-0.1.6.dist-info/RECORD
