Metadata-Version: 2.1
Name: install-scripts
Version: 0.1.6
Summary: A collection of installer scripts
Home-page: https://gitlab.namibsun.net/namibsun/python/install-scripts
Author: Hermann Krumrey
Author-email: hermann@krumreyh.com
License: GNU GPL3
Platform: UNKNOWN
Classifier: License :: OSI Approved :: GNU General Public License v3 (GPLv3)
Requires-Dist: typing
Requires-Dist: colorama
